konnektor/__init__.py
konnektor/_version.py
konnektor/data/__init__.py
konnektor/data/benzenes_RHFE.sdf
konnektor/data/charged_ligands.sdf
konnektor/data/hif2a_ligands.sdf
konnektor/network_analysis/__init__.py
konnektor/network_analysis/network_analysis.py
konnektor/network_planners/NetworkPlanner.py
konnektor/network_planners/__init__.py
konnektor/network_planners/_networkx_implementations/__init__.py
konnektor/network_planners/_networkx_implementations/_abstract_network_algorithm.py
konnektor/network_planners/_networkx_implementations/bipartite_match_algorithm.py
konnektor/network_planners/_networkx_implementations/cyclic_network_algorithm.py
konnektor/network_planners/_networkx_implementations/mst_network_algorithm.py
konnektor/network_planners/_networkx_implementations/n_nodes_edges_network_algorithm.py
konnektor/network_planners/_networkx_implementations/radial_network_algorithm.py
konnektor/network_planners/concatenators/__init__.py
konnektor/network_planners/concatenators/_abstract_network_concatenator.py
konnektor/network_planners/concatenators/cyclic_concatenator.py
konnektor/network_planners/concatenators/max_concatenator.py
konnektor/network_planners/concatenators/mst_concatenator.py
konnektor/network_planners/generators/__init__.py
konnektor/network_planners/generators/_abstract_network_generator.py
konnektor/network_planners/generators/_parallel_mapping_pattern.py
konnektor/network_planners/generators/clustered_network_generator.py
konnektor/network_planners/generators/cyclic_network_generator.py
konnektor/network_planners/generators/explicit_network_generator.py
konnektor/network_planners/generators/heuristic_maximal_network_generator.py
konnektor/network_planners/generators/maximal_network_generator.py
konnektor/network_planners/generators/minimal_spanning_tree_network_generator.py
konnektor/network_planners/generators/n_node_edges_network_generator.py
konnektor/network_planners/generators/redundant_minimal_spanning_tree_network_generator.py
konnektor-0.1.0.dist-info/LICENSE
konnektor-0.1.0.dist-info/METADATA
konnektor-0.1.0.dist-info/WHEEL
konnektor-0.1.0.dist-info/top_level.txt
konnektor-0.1.0.dist-info/RECORD
