Metadata-Version: 2.1
Name: konnektor
Version: 0.1.0
Summary: Konnektor is a package for calculating networks.
Author-email: Benjamin Ries <benjamin-ries@outlook.com>, Hannah Baumann <hannah.baumann@omsf.io>, David Swenson <dwhswenson@gmail.com>, Irfan Alibay <irfan.alibay@gmail.com>, Mike Henry <mike.henry@choderalab.org>, Richard J Gowers <richardjgowers@gmail.com>
Project-URL: Homepage, https://github.com/OpenFreeEnergy/konnektor
Classifier: Programming Language :: Python :: 3
Classifier: License :: OSI Approved :: MIT License
Classifier: Operating System :: OS Independent
Requires-Python: >=3.9
License-File: LICENSE
Requires-Dist: gufe
Requires-Dist: numpy
Requires-Dist: rdkit
Requires-Dist: networkx
Requires-Dist: scikit-mol
Requires-Dist: scikit-learn
Requires-Dist: ipycytoscape
Provides-Extra: dev
Requires-Dist: black ; extra == 'dev'
Requires-Dist: pre-commit ; extra == 'dev'
Provides-Extra: test
Requires-Dist: pytest ; extra == 'test'
Requires-Dist: pytest-cov[all] ; extra == 'test'
